[
  {
    "date": "2026-01-05T00:00:00",
    "symbol": "PNJ",
    "priceHigh": 98.5,
    "priceLow": 96.5,
    "priceOpen": 97.7,
    "priceAverage": 97.61243853578583,
    "priceClose": 98.5,
    "priceBasic": 97,
    "totalVolume": 649100,
    "dealVolume": 549100,
    "putthroughVolume": 100000,
    "totalValue": 63370990000,
    "putthroughValue": 9772000000,
    "buyForeignQuantity": 110910,
    "buyForeignValue": 10826195558.004007,
    "sellForeignQuantity": 139500,
    "sellForeignValue": 13616935175.742123,
    "buyCount": 1034,
    "buyQuantity": 852722,
    "sellCount": 976,
    "sellQuantity": 1308323,
    "adjRatio": 1.0097087379,
    "currentForeignRoom": 22,
    "propTradingNetDealValue": 887010000,
    "propTradingNetPTValue": 0,
    "propTradingNetValue": 887010000,
    "unit": 1000,
    "priceChange": null,
    "returnPct": null
  },
  {
    "date": "2026-01-06T00:00:00",
    "symbol": "PNJ",
    "priceHigh": 99,
    "priceLow": 97.4,
    "priceOpen": 98,
    "priceAverage": 98.15851813201148,
    "priceClose": 98.7,
    "priceBasic": 98.5,
    "totalVolume": 783900,
    "dealVolume": 383300,
    "putthroughVolume": 400600,
    "totalValue": 76948628200,
    "putthroughValue": 39324468200,
    "buyForeignQuantity": 464720,
    "buyForeignValue": 45616226546.30837,
    "sellForeignQuantity": 456766,
    "sellForeignValue": 44835473693.08636,
    "buyCount": 730,
    "buyQuantity": 1068157,
    "sellCount": 879,
    "sellQuantity": 1442681,
    "adjRatio": 1.0097087379,
    "currentForeignRoom": 52,
    "propTradingNetDealValue": -120830000,
    "propTradingNetPTValue": 0,
    "propTradingNetValue": -120830000,
    "unit": 1000,
    "priceChange": 0.20000000000000284,
    "returnPct": 0.2030456852791907
  },
  {
    "date": "2026-01-07T00:00:00",
    "symbol": "PNJ",
    "priceHigh": 103,
    "priceLow": 98.4,
    "priceOpen": 98.7,
    "priceAverage": 101.26704671417261,
    "priceClose": 102.6,
    "priceBasic": 98.7,
    "totalVolume": 1263000,
    "dealVolume": 1263000,
    "putthroughVolume": 0,
    "totalValue": 127900280000,
    "putthroughValue": 0,
    "buyForeignQuantity": 99977,
    "buyForeignValue": 10124375529.342834,
    "sellForeignQuantity": 209780,
    "sellForeignValue": 21243801059.699127,
    "buyCount": 1330,
    "buyQuantity": 1778950,
    "sellCount": 1880,
    "sellQuantity": 2100737,
    "adjRatio": 1.0097087379,
    "currentForeignRoom": 1,
    "propTradingNetDealValue": 127210000,
    "propTradingNetPTValue": 0,
    "propTradingNetValue": 127210000,
    "unit": 1000,
    "priceChange": 3.8999999999999915,
    "returnPct": 3.9513677811550068
  },
  {
    "date": "2026-01-08T00:00:00",
    "symbol": "PNJ",
    "priceHigh": 104,
    "priceLow": 102,
    "priceOpen": 102.6,
    "priceAverage": 103.17641585398586,
    "priceClose": 104,
    "priceBasic": 102.6,
    "totalVolume": 1117766,
    "dealVolume": 1117700,
    "putthroughVolume": 66,
    "totalValue": 115327104400,
    "putthroughValue": 6824400,
    "buyForeignQuantity": 128578,
    "buyForeignValue": 13266217197.673794,
    "sellForeignQuantity": 87620,
    "sellForeignValue": 9040317557.126242,
    "buyCount": 848,
    "buyQuantity": 1438757,
    "sellCount": 1413,
    "sellQuantity": 1766644,
    "adjRatio": 1.0097087379,
    "currentForeignRoom": 0,
    "propTradingNetDealValue": 2128720000,
    "propTradingNetPTValue": -6824000,
    "propTradingNetValue": 2121896000,
    "unit": 1000,
    "priceChange": 1.4000000000000057,
    "returnPct": 1.3645224171540018
  },
  {
    "date": "2026-01-09T00:00:00",
    "symbol": "PNJ",
    "priceHigh": 104.2,
    "priceLow": 102,
    "priceOpen": 103.2,
    "priceAverage": 102.94248006598845,
    "priceClose": 103,
    "priceBasic": 103,
    "totalVolume": 767400,
    "dealVolume": 727400,
    "putthroughVolume": 40000,
    "totalValue": 79000360000,
    "putthroughValue": 4120000000,
    "buyForeignQuantity": 127605,
    "buyForeignValue": 13135975168.820456,
    "sellForeignQuantity": 65497,
    "sellForeignValue": 6742423616.882046,
    "buyCount": 826,
    "buyQuantity": 1020524,
    "sellCount": 1150,
    "sellQuantity": 1295665,
    "adjRatio": 1,
    "currentForeignRoom": 15,
    "propTradingNetDealValue": -869210000,
    "propTradingNetPTValue": 0,
    "propTradingNetValue": -869210000,
    "unit": 1000,
    "priceChange": -1,
    "returnPct": -0.9615384615384616
  },
  {
    "date": "2026-01-12T00:00:00",
    "symbol": "PNJ",
    "priceHigh": 104,
    "priceLow": 99.2,
    "priceOpen": 104,
    "priceAverage": 101.01782575947779,
    "priceClose": 103.2,
    "priceBasic": 103,
    "totalVolume": 1194900,
    "dealVolume": 1194900,
    "putthroughVolume": 0,
    "totalValue": 120706200000,
    "putthroughValue": 0,
    "buyForeignQuantity": 135100,
    "buyForeignValue": 13647508260.105448,
    "sellForeignQuantity": 91440,
    "sellForeignValue": 9237069987.446648,
    "buyCount": 1570,
    "buyQuantity": 1808975,
    "sellCount": 1512,
    "sellQuantity": 1893546,
    "adjRatio": 1,
    "currentForeignRoom": 65,
    "propTradingNetDealValue": -3220480000,
    "propTradingNetPTValue": 0,
    "propTradingNetValue": -3220480000,
    "unit": 1000,
    "priceChange": 0.20000000000000284,
    "returnPct": 0.19417475728155617
  },
  {
    "date": "2026-01-13T00:00:00",
    "symbol": "PNJ",
    "priceHigh": 103.5,
    "priceLow": 100.4,
    "priceOpen": 100.5,
    "priceAverage": 102.17578856712241,
    "priceClose": 102.9,
    "priceBasic": 103.2,
    "totalVolume": 928900,
    "dealVolume": 928900,
    "putthroughVolume": 0,
    "totalValue": 94911090000,
    "putthroughValue": 0,
    "buyForeignQuantity": 90950,
    "buyForeignValue": 9292887970.179783,
    "sellForeignQuantity": 468105,
    "sellForeignValue": 47828997507.21283,
    "buyCount": 1540,
    "buyQuantity": 1428702,
    "sellCount": 1402,
    "sellQuantity": 1668044,
    "adjRatio": 1,
    "currentForeignRoom": 0,
    "propTradingNetDealValue": 2633130000,
    "propTradingNetPTValue": 0,
    "propTradingNetValue": 2633130000,
    "unit": 1000,
    "priceChange": -0.29999999999999716,
    "returnPct": -0.2906976744186019
  },
  {
    "date": "2026-01-14T00:00:00",
    "symbol": "PNJ",
    "priceHigh": 103,
    "priceLow": 100.5,
    "priceOpen": 101.1,
    "priceAverage": 101.58088495575223,
    "priceClose": 101.5,
    "priceBasic": 102.9,
    "totalVolume": 565000,
    "dealVolume": 565000,
    "putthroughVolume": 0,
    "totalValue": 57393200000,
    "putthroughValue": 0,
    "buyForeignQuantity": 7700,
    "buyForeignValue": 782172814.159292,
    "sellForeignQuantity": 209600,
    "sellForeignValue": 21291353486.725662,
    "buyCount": 765,
    "buyQuantity": 1268460,
    "sellCount": 988,
    "sellQuantity": 1524312,
    "adjRatio": 1,
    "currentForeignRoom": 83705,
    "propTradingNetDealValue": -993320000,
    "propTradingNetPTValue": 0,
    "propTradingNetValue": -993320000,
    "unit": 1000,
    "priceChange": -1.4000000000000057,
    "returnPct": -1.3605442176870803
  },
  {
    "date": "2026-01-15T00:00:00",
    "symbol": "PNJ",
    "priceHigh": 102,
    "priceLow": 99.5,
    "priceOpen": 100.1,
    "priceAverage": 100.6317626758694,
    "priceClose": 101.5,
    "priceBasic": 101.5,
    "totalVolume": 753400,
    "dealVolume": 753400,
    "putthroughVolume": 0,
    "totalValue": 75815970000,
    "putthroughValue": 0,
    "buyForeignQuantity": 61055,
    "buyForeignValue": 6144072270.175206,
    "sellForeignQuantity": 180300,
    "sellForeignValue": 18143906810.45925,
    "buyCount": 1116,
    "buyQuantity": 1447382,
    "sellCount": 999,
    "sellQuantity": 1488788,
    "adjRatio": 1,
    "currentForeignRoom": 550,
    "propTradingNetDealValue": -4643820000,
    "propTradingNetPTValue": 0,
    "propTradingNetValue": -4643820000,
    "unit": 1000,
    "priceChange": 0,
    "returnPct": 0
  },
  {
    "date": "2026-01-16T00:00:00",
    "symbol": "PNJ",
    "priceHigh": 108.6,
    "priceLow": 101.5,
    "priceOpen": 101.5,
    "priceAverage": 107.59092472296523,
    "priceClose": 107.7,
    "priceBasic": 101.5,
    "totalVolume": 5133800,
    "dealVolume": 4710600,
    "putthroughVolume": 423200,
    "totalValue": 552491734000,
    "putthroughValue": 45673924000,
    "buyForeignQuantity": 888795,
    "buyForeignValue": 95626275939.14789,
    "sellForeignQuantity": 2800144,
    "sellForeignValue": 301270082317.46277,
    "buyCount": 2631,
    "buyQuantity": 6302536,
    "sellCount": 2694,
    "sellQuantity": 5838927,
    "adjRatio": 1,
    "currentForeignRoom": 65,
    "propTradingNetDealValue": -549000000,
    "propTradingNetPTValue": 0,
    "propTradingNetValue": -549000000,
    "unit": 1000,
    "priceChange": 6.200000000000003,
    "returnPct": 6.108374384236456
  },
  {
    "date": "2026-01-19T00:00:00",
    "symbol": "PNJ",
    "priceHigh": 115,
    "priceLow": 107,
    "priceOpen": 107.7,
    "priceAverage": 111.00055928023066,
    "priceClose": 114.2,
    "priceBasic": 107.7,
    "totalVolume": 2948700,
    "dealVolume": 2878700,
    "putthroughVolume": 70000,
    "totalValue": 327122310000,
    "putthroughValue": 7585000000,
    "buyForeignQuantity": 481915,
    "buyForeignValue": 53492834525.53236,
    "sellForeignQuantity": 6900,
    "sellForeignValue": 765903859.0335915,
    "buyCount": 2972,
    "buyQuantity": 4227593,
    "sellCount": 2206,
    "sellQuantity": 3657259,
    "adjRatio": 1,
    "currentForeignRoom": 188795,
    "propTradingNetDealValue": -1603160000,
    "propTradingNetPTValue": 0,
    "propTradingNetValue": -1603160000,
    "unit": 1000,
    "priceChange": 6.5,
    "returnPct": 6.035283194057567
  },
  {
    "date": "2026-01-20T00:00:00",
    "symbol": "PNJ",
    "priceHigh": 114,
    "priceLow": 110.7,
    "priceOpen": 112.9,
    "priceAverage": 111.77292373544918,
    "priceClose": 111.9,
    "priceBasic": 114.2,
    "totalVolume": 2224204,
    "dealVolume": 1915700,
    "putthroughVolume": 308504,
    "totalValue": 247923522616,
    "putthroughValue": 33800132616,
    "buyForeignQuantity": 425504,
    "buyForeignValue": 47559826141.12857,
    "sellForeignQuantity": 1245437,
    "sellForeignValue": 139206134818.30664,
    "buyCount": 2235,
    "buyQuantity": 2684260,
    "sellCount": 2131,
    "sellQuantity": 3827846,
    "adjRatio": 1,
    "currentForeignRoom": 197940,
    "propTradingNetDealValue": -2141200000,
    "propTradingNetPTValue": 0,
    "propTradingNetValue": -2141200000,
    "unit": 1000,
    "priceChange": -2.299999999999997,
    "returnPct": -2.0140105078809083
  },
  {
    "date": "2026-01-21T00:00:00",
    "symbol": "PNJ",
    "priceHigh": 112.8,
    "priceLow": 108.5,
    "priceOpen": 109.7,
    "priceAverage": 109.99089769307925,
    "priceClose": 109.9,
    "priceBasic": 111.9,
    "totalVolume": 2213000,
    "dealVolume": 1994000,
    "putthroughVolume": 219000,
    "totalValue": 243281640000,
    "putthroughValue": 23959790000,
    "buyForeignQuantity": 216110,
    "buyForeignValue": 23770132900.451355,
    "sellForeignQuantity": 710600,
    "sellForeignValue": 78159531900.7021,
    "buyCount": 1527,
    "buyQuantity": 2808116,
    "sellCount": 1694,
    "sellQuantity": 3645341,
    "adjRatio": 1,
    "currentForeignRoom": 2179179,
    "propTradingNetDealValue": 337470000,
    "propTradingNetPTValue": 0,
    "propTradingNetValue": 337470000,
    "unit": 1000,
    "priceChange": -2,
    "returnPct": -1.7873100983020553
  },
  {
    "date": "2026-01-22T00:00:00",
    "symbol": "PNJ",
    "priceHigh": 111.9,
    "priceLow": 107.7,
    "priceOpen": 110.2,
    "priceAverage": 109.50117269472905,
    "priceClose": 110.4,
    "priceBasic": 109.9,
    "totalVolume": 1620200,
    "dealVolume": 1620200,
    "putthroughVolume": 0,
    "totalValue": 177413800000,
    "putthroughValue": 0,
    "buyForeignQuantity": 418248,
    "buyForeignValue": 45798646477.22504,
    "sellForeignQuantity": 557900,
    "sellForeignValue": 61090704246.389336,
    "buyCount": 1996,
    "buyQuantity": 2245234,
    "sellCount": 1523,
    "sellQuantity": 2565535,
    "adjRatio": 1,
    "currentForeignRoom": 1808038,
    "propTradingNetDealValue": -5203950000,
    "propTradingNetPTValue": 0,
    "propTradingNetValue": -5203950000,
    "unit": 1000,
    "priceChange": 0.5,
    "returnPct": 0.4549590536851683
  },
  {
    "date": "2026-01-23T00:00:00",
    "symbol": "PNJ",
    "priceHigh": 115,
    "priceLow": 108.9,
    "priceOpen": 110,
    "priceAverage": 112.04505788876277,
    "priceClose": 112.4,
    "priceBasic": 110.4,
    "totalVolume": 2406500,
    "dealVolume": 2202500,
    "putthroughVolume": 204000,
    "totalValue": 269600216000,
    "putthroughValue": 22820976000,
    "buyForeignQuantity": 706800,
    "buyForeignValue": 79193446915.77753,
    "sellForeignQuantity": 917200,
    "sellForeignValue": 102767727095.57321,
    "buyCount": 2236,
    "buyQuantity": 3251617,
    "sellCount": 2253,
    "sellQuantity": 3873935,
    "adjRatio": 1,
    "currentForeignRoom": 2491387,
    "propTradingNetDealValue": 5725720000,
    "propTradingNetPTValue": 0,
    "propTradingNetValue": 5725720000,
    "unit": 1000,
    "priceChange": 2,
    "returnPct": 1.8115942028985508
  },
  {
    "date": "2026-01-26T00:00:00",
    "symbol": "PNJ",
    "priceHigh": 117.8,
    "priceLow": 112.8,
    "priceOpen": 113.8,
    "priceAverage": 115.48873541712526,
    "priceClose": 116.8,
    "priceBasic": 112.4,
    "totalVolume": 3834400,
    "dealVolume": 3634400,
    "putthroughVolume": 200000,
    "totalValue": 442967860000,
    "putthroughValue": 23235600000,
    "buyForeignQuantity": 1133446,
    "buyForeignValue": 130900245203.59894,
    "sellForeignQuantity": 479500,
    "sellForeignValue": 55376848632.51156,
    "buyCount": 4169,
    "buyQuantity": 6273820,
    "sellCount": 2424,
    "sellQuantity": 5640913,
    "adjRatio": 1,
    "currentForeignRoom": 2606962,
    "propTradingNetDealValue": 2270620000,
    "propTradingNetPTValue": 0,
    "propTradingNetValue": 2270620000,
    "unit": 1000,
    "priceChange": 4.3999999999999915,
    "returnPct": 3.914590747330953
  },
  {
    "date": "2026-01-27T00:00:00",
    "symbol": "PNJ",
    "priceHigh": 117.4,
    "priceLow": 115.4,
    "priceOpen": 116.8,
    "priceAverage": 116.51990576239766,
    "priceClose": 116,
    "priceBasic": 116.8,
    "totalVolume": 1344600,
    "dealVolume": 1294600,
    "putthroughVolume": 50000,
    "totalValue": 156686670000,
    "putthroughValue": 5840000000,
    "buyForeignQuantity": 617823,
    "buyForeignValue": 71988677737.8418,
    "sellForeignQuantity": 316000,
    "sellForeignValue": 36820290220.917656,
    "buyCount": 2226,
    "buyQuantity": 1809676,
    "sellCount": 1498,
    "sellQuantity": 2940518,
    "adjRatio": 1,
    "currentForeignRoom": 2407595,
    "propTradingNetDealValue": -4454640000,
    "propTradingNetPTValue": 0,
    "propTradingNetValue": -4454640000,
    "unit": 1000,
    "priceChange": -0.7999999999999972,
    "returnPct": -0.6849315068493127
  },
  {
    "date": "2026-01-28T00:00:00",
    "symbol": "PNJ",
    "priceHigh": 121.1,
    "priceLow": 114,
    "priceOpen": 116.9,
    "priceAverage": 118.27804746940126,
    "priceClose": 118.5,
    "priceBasic": 116,
    "totalVolume": 2418400,
    "dealVolume": 2418400,
    "putthroughVolume": 0,
    "totalValue": 286043630000,
    "putthroughValue": 0,
    "buyForeignQuantity": 121850,
    "buyForeignValue": 14412180084.146544,
    "sellForeignQuantity": 182800,
    "sellForeignValue": 21621227077.40655,
    "buyCount": 2706,
    "buyQuantity": 3496834,
    "sellCount": 1961,
    "sellQuantity": 3995654,
    "adjRatio": 1,
    "currentForeignRoom": 2813145,
    "propTradingNetDealValue": -2954490000,
    "propTradingNetPTValue": 0,
    "propTradingNetValue": -2954490000,
    "unit": 1000,
    "priceChange": 2.5,
    "returnPct": 2.1551724137931036
  },
  {
    "date": "2026-01-29T00:00:00",
    "symbol": "PNJ",
    "priceHigh": 126.5,
    "priceLow": 119,
    "priceOpen": 119.9,
    "priceAverage": 123.38055833269246,
    "priceClose": 126.5,
    "priceBasic": 118.5,
    "totalVolume": 6691500,
    "dealVolume": 6501500,
    "putthroughVolume": 190000,
    "totalValue": 825818260000,
    "putthroughValue": 23659560000,
    "buyForeignQuantity": 2315261,
    "buyForeignValue": 285658194865.90784,
    "sellForeignQuantity": 684670,
    "sellForeignValue": 84474966873.64455,
    "buyCount": 6572,
    "buyQuantity": 9797673,
    "sellCount": 2814,
    "sellQuantity": 7390415,
    "adjRatio": 1,
    "currentForeignRoom": 713634,
    "propTradingNetDealValue": -6473070000,
    "propTradingNetPTValue": 0,
    "propTradingNetValue": -6473070000,
    "unit": 1000,
    "priceChange": 8,
    "returnPct": 6.751054852320674
  },
  {
    "date": "2026-01-30T00:00:00",
    "symbol": "PNJ",
    "priceHigh": 127,
    "priceLow": 121.5,
    "priceOpen": 124.8,
    "priceAverage": 124.90147739742525,
    "priceClose": 127,
    "priceBasic": 126.5,
    "totalVolume": 3843809,
    "dealVolume": 3736300,
    "putthroughVolume": 107509,
    "totalValue": 480142309100,
    "putthroughValue": 13472919100,
    "buyForeignQuantity": 1242144,
    "buyForeignValue": 155145620740.3474,
    "sellForeignQuantity": 1016540,
    "sellForeignValue": 126967347833.57867,
    "buyCount": 3440,
    "buyQuantity": 6777173,
    "sellCount": 2975,
    "sellQuantity": 5663933,
    "adjRatio": 1,
    "currentForeignRoom": 169705,
    "propTradingNetDealValue": 92633100000,
    "propTradingNetPTValue": 0,
    "propTradingNetValue": 92633100000,
    "unit": 1000,
    "priceChange": 0.5,
    "returnPct": 0.3952569169960474
  },
  {
    "date": "2026-02-02T00:00:00",
    "symbol": "PNJ",
    "priceHigh": 123.6,
    "priceLow": 118.2,
    "priceOpen": 123.3,
    "priceAverage": 119.00682460787523,
    "priceClose": 118.2,
    "priceBasic": 127,
    "totalVolume": 3390500,
    "dealVolume": 3359900,
    "putthroughVolume": 30600,
    "totalValue": 403467950000,
    "putthroughValue": 3616920000,
    "buyForeignQuantity": 962100,
    "buyForeignValue": 114496465955.23676,
    "sellForeignQuantity": 435300,
    "sellForeignValue": 51803670751.80809,
    "buyCount": 3027,
    "buyQuantity": 3707105,
    "sellCount": 3118,
    "sellQuantity": 6701248,
    "adjRatio": 1,
    "currentForeignRoom": 208250,
    "propTradingNetDealValue": -980300000,
    "propTradingNetPTValue": 0,
    "propTradingNetValue": -980300000,
    "unit": 1000,
    "priceChange": -8.799999999999997,
    "returnPct": -6.929133858267714
  },
  {
    "date": "2026-02-03T00:00:00",
    "symbol": "PNJ",
    "priceHigh": 120,
    "priceLow": 113.5,
    "priceOpen": 116.2,
    "priceAverage": 117.4233477958271,
    "priceClose": 120,
    "priceBasic": 118.2,
    "totalVolume": 7813100,
    "dealVolume": 6753100,
    "putthroughVolume": 1060000,
    "totalValue": 923920510000,
    "putthroughValue": 130948900000,
    "buyForeignQuantity": 912910,
    "buyForeignValue": 107196948436.28853,
    "sellForeignQuantity": 2860000,
    "sellForeignValue": 335830774696.0655,
    "buyCount": 7104,
    "buyQuantity": 9760262,
    "sellCount": 6420,
    "sellQuantity": 9178937,
    "adjRatio": 1,
    "currentForeignRoom": 40,
    "propTradingNetDealValue": 1498090000,
    "propTradingNetPTValue": -95770000000,
    "propTradingNetValue": -94271910000,
    "unit": 1000,
    "priceChange": 1.7999999999999972,
    "returnPct": 1.5228426395939063
  },
  {
    "date": "2026-02-04T00:00:00",
    "symbol": "PNJ",
    "priceHigh": 121,
    "priceLow": 119,
    "priceOpen": 120.7,
    "priceAverage": 120.0722866322112,
    "priceClose": 119.7,
    "priceBasic": 120,
    "totalVolume": 2925600,
    "dealVolume": 2147700,
    "putthroughVolume": 777900,
    "totalValue": 351460412500,
    "putthroughValue": 93581162500,
    "buyForeignQuantity": 943300,
    "buyForeignValue": 113264187980.16483,
    "sellForeignQuantity": 993300,
    "sellForeignValue": 119267802311.77539,
    "buyCount": 2286,
    "buyQuantity": 3785966,
    "sellCount": 2562,
    "sellQuantity": 4676057,
    "adjRatio": 1,
    "currentForeignRoom": 0,
    "propTradingNetDealValue": -17624420000,
    "propTradingNetPTValue": 0,
    "propTradingNetValue": -17624420000,
    "unit": 1000,
    "priceChange": -0.29999999999999716,
    "returnPct": -0.2499999999999976
  },
  {
    "date": "2026-02-05T00:00:00",
    "symbol": "PNJ",
    "priceHigh": 120,
    "priceLow": 114.4,
    "priceOpen": 119.9,
    "priceAverage": 116.00894709271871,
    "priceClose": 116.2,
    "priceBasic": 119.7,
    "totalVolume": 2998200,
    "dealVolume": 2863500,
    "putthroughVolume": 134700,
    "totalValue": 347818032300,
    "putthroughValue": 15626412300,
    "buyForeignQuantity": 546150,
    "buyForeignValue": 63358286454.68832,
    "sellForeignQuantity": 1149100,
    "sellForeignValue": 133305881104.24306,
    "buyCount": 3051,
    "buyQuantity": 4385464,
    "sellCount": 2994,
    "sellQuantity": 5565752,
    "adjRatio": 1,
    "currentForeignRoom": 0,
    "propTradingNetDealValue": 3504830000,
    "propTradingNetPTValue": 0,
    "propTradingNetValue": 3504830000,
    "unit": 1000,
    "priceChange": -3.5,
    "returnPct": -2.923976608187134
  },
  {
    "date": "2026-02-06T00:00:00",
    "symbol": "PNJ",
    "priceHigh": 113,
    "priceLow": 108.1,
    "priceOpen": 113,
    "priceAverage": 109.46457980935703,
    "priceClose": 108.9,
    "priceBasic": 116.2,
    "totalVolume": 5064600,
    "dealVolume": 5025100,
    "putthroughVolume": 39500,
    "totalValue": 554394327500,
    "putthroughValue": 4323867500,
    "buyForeignQuantity": 491800,
    "buyForeignValue": 53834680350.24178,
    "sellForeignQuantity": 1737700,
    "sellForeignValue": 190216600334.7197,
    "buyCount": 4392,
    "buyQuantity": 5396325,
    "sellCount": 4189,
    "sellQuantity": 7343925,
    "adjRatio": 1,
    "currentForeignRoom": 2107730,
    "propTradingNetDealValue": 1011970000,
    "propTradingNetPTValue": 0,
    "propTradingNetValue": 1011970000,
    "unit": 1000,
    "priceChange": -7.299999999999997,
    "returnPct": -6.282271944922544
  },
  {
    "date": "2026-02-09T00:00:00",
    "symbol": "PNJ",
    "priceHigh": 113.8,
    "priceLow": 110,
    "priceOpen": 110.5,
    "priceAverage": 112.10416481069042,
    "priceClose": 112.9,
    "priceBasic": 108.9,
    "totalVolume": 2330000,
    "dealVolume": 2245000,
    "putthroughVolume": 85000,
    "totalValue": 261202690000,
    "putthroughValue": 9528840000,
    "buyForeignQuantity": 707800,
    "buyForeignValue": 79347327853.00668,
    "sellForeignQuantity": 907230,
    "sellForeignValue": 101704261441.20267,
    "buyCount": 2204,
    "buyQuantity": 3023844,
    "sellCount": 2733,
    "sellQuantity": 3315815,
    "adjRatio": 1,
    "currentForeignRoom": 1973540,
    "propTradingNetDealValue": 660270000,
    "propTradingNetPTValue": 0,
    "propTradingNetValue": 660270000,
    "unit": 1000,
    "priceChange": 4,
    "returnPct": 3.6730945821854912
  },
  {
    "date": "2026-02-10T00:00:00",
    "symbol": "PNJ",
    "priceHigh": 114.4,
    "priceLow": 105,
    "priceOpen": 113,
    "priceAverage": 113.00776949032142,
    "priceClose": 112.9,
    "priceBasic": 112.9,
    "totalVolume": 2252400,
    "dealVolume": 2252400,
    "putthroughVolume": 0,
    "totalValue": 254538700000,
    "putthroughValue": 0,
    "buyForeignQuantity": 1154700,
    "buyForeignValue": 130490071430.47417,
    "sellForeignQuantity": 660770,
    "sellForeignValue": 74672143846.11969,
    "buyCount": 2365,
    "buyQuantity": 3051398,
    "sellCount": 2922,
    "sellQuantity": 3529538,
    "adjRatio": 1,
    "currentForeignRoom": 2038290,
    "propTradingNetDealValue": 4273730000,
    "propTradingNetPTValue": 0,
    "propTradingNetValue": 4273730000,
    "unit": 1000,
    "priceChange": 0,
    "returnPct": 0
  },
  {
    "date": "2026-02-11T00:00:00",
    "symbol": "PNJ",
    "priceHigh": 115.9,
    "priceLow": 111,
    "priceOpen": 111.1,
    "priceAverage": 112.66113306982872,
    "priceClose": 115.9,
    "priceBasic": 112.9,
    "totalVolume": 2808300,
    "dealVolume": 2808300,
    "putthroughVolume": 0,
    "totalValue": 316386260000,
    "putthroughValue": 0,
    "buyForeignQuantity": 923800,
    "buyForeignValue": 104076354729.90778,
    "sellForeignQuantity": 1342700,
    "sellForeignValue": 151270103372.85904,
    "buyCount": 2276,
    "buyQuantity": 3992933,
    "sellCount": 2493,
    "sellQuantity": 3569034,
    "adjRatio": 1,
    "currentForeignRoom": 3007460,
    "propTradingNetDealValue": 17287510000,
    "propTradingNetPTValue": 0,
    "propTradingNetValue": 17287510000,
    "unit": 1000,
    "priceChange": 3,
    "returnPct": 2.657218777679362
  },
  {
    "date": "2026-02-12T00:00:00",
    "symbol": "PNJ",
    "priceHigh": 119.9,
    "priceLow": 113,
    "priceOpen": 115.9,
    "priceAverage": 117.7391187870497,
    "priceClose": 118.5,
    "priceBasic": 115.9,
    "totalVolume": 2014400,
    "dealVolume": 1754400,
    "putthroughVolume": 260000,
    "totalValue": 237226950000,
    "putthroughValue": 30665440000,
    "buyForeignQuantity": 677120,
    "buyForeignValue": 79723512113.0871,
    "sellForeignQuantity": 644800,
    "sellForeignValue": 75918183793.88965,
    "buyCount": 2369,
    "buyQuantity": 3021472,
    "sellCount": 2522,
    "sellQuantity": 3523957,
    "adjRatio": 1,
    "currentForeignRoom": 3746370,
    "propTradingNetDealValue": 20685160000,
    "propTradingNetPTValue": 0,
    "propTradingNetValue": 20685160000,
    "unit": 1000,
    "priceChange": 2.5999999999999943,
    "returnPct": 2.2433132010353702
  },
  {
    "date": "2026-02-13T00:00:00",
    "symbol": "PNJ",
    "priceHigh": 120,
    "priceLow": 115.4,
    "priceOpen": 117,
    "priceAverage": 117.8424761353775,
    "priceClose": 120,
    "priceBasic": 118.5,
    "totalVolume": 1827500,
    "dealVolume": 1728500,
    "putthroughVolume": 99000,
    "totalValue": 215363612000,
    "putthroughValue": 11672892000,
    "buyForeignQuantity": 676201,
    "buyForeignValue": 79685200205.2184,
    "sellForeignQuantity": 701400,
    "sellForeignValue": 82654712761.35378,
    "buyCount": 1857,
    "buyQuantity": 2531655,
    "sellCount": 1625,
    "sellQuantity": 2818614,
    "adjRatio": 1,
    "currentForeignRoom": 3455869,
    "propTradingNetDealValue": 5425950000,
    "propTradingNetPTValue": 0,
    "propTradingNetValue": 5425950000,
    "unit": 1000,
    "priceChange": 1.5,
    "returnPct": 1.2658227848101267
  },
  {
    "date": "2026-02-23T00:00:00",
    "symbol": "PNJ",
    "priceHigh": 121.9,
    "priceLow": 119.3,
    "priceOpen": 120.3,
    "priceAverage": 120.27894911596248,
    "priceClose": 120.2,
    "priceBasic": 120,
    "totalVolume": 1234700,
    "dealVolume": 1204700,
    "putthroughVolume": 30000,
    "totalValue": 148500530000,
    "putthroughValue": 3600480000,
    "buyForeignQuantity": 106400,
    "buyForeignValue": 12797680185.938408,
    "sellForeignQuantity": 433800,
    "sellForeignValue": 52177008126.504524,
    "buyCount": 1913,
    "buyQuantity": 1552117,
    "sellCount": 1919,
    "sellQuantity": 2171493,
    "adjRatio": 1,
    "currentForeignRoom": 4474370,
    "propTradingNetDealValue": 5076080000,
    "propTradingNetPTValue": 0,
    "propTradingNetValue": 5076080000,
    "unit": 1000,
    "priceChange": 0.20000000000000284,
    "returnPct": 0.16666666666666904
  },
  {
    "date": "2026-02-24T00:00:00",
    "symbol": "PNJ",
    "priceHigh": 121.8,
    "priceLow": 118.8,
    "priceOpen": 120.2,
    "priceAverage": 120.18755939772142,
    "priceClose": 120.5,
    "priceBasic": 120.2,
    "totalVolume": 1898300,
    "dealVolume": 1746700,
    "putthroughVolume": 151600,
    "totalValue": 228129096800,
    "putthroughValue": 18197486800,
    "buyForeignQuantity": 410000,
    "buyForeignValue": 49276899353.06578,
    "sellForeignQuantity": 930667,
    "sellForeignValue": 111854595341.9992,
    "buyCount": 2030,
    "buyQuantity": 2521295,
    "sellCount": 2966,
    "sellQuantity": 3097178,
    "adjRatio": 1,
    "currentForeignRoom": 4140970,
    "propTradingNetDealValue": -2803770000,
    "propTradingNetPTValue": 0,
    "propTradingNetValue": -2803770000,
    "unit": 1000,
    "priceChange": 0.29999999999999716,
    "returnPct": 0.2495840266222938
  },
  {
    "date": "2026-02-25T00:00:00",
    "symbol": "PNJ",
    "priceHigh": 121.3,
    "priceLow": 112.1,
    "priceOpen": 121.3,
    "priceAverage": 117.1163619449712,
    "priceClose": 119.5,
    "priceBasic": 120.5,
    "totalVolume": 3215900,
    "dealVolume": 2794900,
    "putthroughVolume": 421000,
    "totalValue": 377003604000,
    "putthroughValue": 49675084000,
    "buyForeignQuantity": 898300,
    "buyForeignValue": 105205627935.16763,
    "sellForeignQuantity": 671940,
    "sellForeignValue": 78695168245.30394,
    "buyCount": 4208,
    "buyQuantity": 4349321,
    "sellCount": 3178,
    "sellQuantity": 5029127,
    "adjRatio": 1,
    "currentForeignRoom": 3827669,
    "propTradingNetDealValue": -22842450000,
    "propTradingNetPTValue": 0,
    "propTradingNetValue": -22842450000,
    "unit": 1000,
    "priceChange": -1,
    "returnPct": -0.8298755186721992
  },
  {
    "date": "2026-02-26T00:00:00",
    "symbol": "PNJ",
    "priceHigh": 121.9,
    "priceLow": 117,
    "priceOpen": 118.8,
    "priceAverage": 119.12192112800176,
    "priceClose": 120,
    "priceBasic": 119.5,
    "totalVolume": 3223400,
    "dealVolume": 2723400,
    "putthroughVolume": 500000,
    "totalValue": 383977640000,
    "putthroughValue": 59561000000,
    "buyForeignQuantity": 1673721,
    "buyForeignValue": 199376860952.28024,
    "sellForeignQuantity": 418358,
    "sellForeignValue": 49835608679.26856,
    "buyCount": 3655,
    "buyQuantity": 6253572,
    "sellCount": 3504,
    "sellQuantity": 4391779,
    "adjRatio": 1,
    "currentForeignRoom": 2831288,
    "propTradingNetDealValue": -3207930000,
    "propTradingNetPTValue": 0,
    "propTradingNetValue": -3207930000,
    "unit": 1000,
    "priceChange": 0.5,
    "returnPct": 0.41841004184100417
  },
  {
    "date": "2026-02-27T00:00:00",
    "symbol": "PNJ",
    "priceHigh": 122.2,
    "priceLow": 119.6,
    "priceOpen": 120.9,
    "priceAverage": 121.24806983034178,
    "priceClose": 121.9,
    "priceBasic": 120,
    "totalVolume": 2649400,
    "dealVolume": 2033500,
    "putthroughVolume": 615900,
    "totalValue": 321234593200,
    "putthroughValue": 74676643200,
    "buyForeignQuantity": 1314973,
    "buyForeignValue": 159437938129.01404,
    "sellForeignQuantity": 71816,
    "sellForeignValue": 8707551382.935825,
    "buyCount": 2790,
    "buyQuantity": 3568703,
    "sellCount": 2618,
    "sellQuantity": 3886637,
    "adjRatio": 1,
    "currentForeignRoom": 2427940,
    "propTradingNetDealValue": -6391840000,
    "propTradingNetPTValue": 0,
    "propTradingNetValue": -6391840000,
    "unit": 1000,
    "priceChange": 1.9000000000000057,
    "returnPct": 1.583333333333338
  },
  {
    "date": "2026-03-02T00:00:00",
    "symbol": "PNJ",
    "priceHigh": 126.9,
    "priceLow": 120,
    "priceOpen": 121.4,
    "priceAverage": 124.73812404361134,
    "priceClose": 124.5,
    "priceBasic": 121.9,
    "totalVolume": 4182400,
    "dealVolume": 4182400,
    "putthroughVolume": 0,
    "totalValue": 521704730000,
    "putthroughValue": 0,
    "buyForeignQuantity": 1175996,
    "buyForeignValue": 146691534922.79077,
    "sellForeignQuantity": 203100,
    "sellForeignValue": 25334312993.25746,
    "buyCount": 5525,
    "buyQuantity": 6711990,
    "sellCount": 3097,
    "sellQuantity": 5878632,
    "adjRatio": 1,
    "currentForeignRoom": 1489860,
    "propTradingNetDealValue": -1159770000,
    "propTradingNetPTValue": 0,
    "propTradingNetValue": -1159770000,
    "unit": 1000,
    "priceChange": 2.5999999999999943,
    "returnPct": 2.1328958162428173
  },
  {
    "date": "2026-03-03T00:00:00",
    "symbol": "PNJ",
    "priceHigh": 124.9,
    "priceLow": 119.5,
    "priceOpen": 124.5,
    "priceAverage": 121.7648383838384,
    "priceClose": 122,
    "priceBasic": 124.5,
    "totalVolume": 1980000,
    "dealVolume": 1980000,
    "putthroughVolume": 0,
    "totalValue": 241094380000,
    "putthroughValue": 0,
    "buyForeignQuantity": 581854,
    "buyForeignValue": 70849358272.9899,
    "sellForeignQuantity": 174100,
    "sellForeignValue": 21199258362.626263,
    "buyCount": 3369,
    "buyQuantity": 3017708,
    "sellCount": 1989,
    "sellQuantity": 3193388,
    "adjRatio": 1,
    "currentForeignRoom": 1142206,
    "propTradingNetDealValue": -2373060000,
    "propTradingNetPTValue": 0,
    "propTradingNetValue": -2373060000,
    "unit": 1000,
    "priceChange": -2.5,
    "returnPct": -2.0080321285140563
  },
  {
    "date": "2026-03-04T00:00:00",
    "symbol": "PNJ",
    "priceHigh": 120.9,
    "priceLow": 114.9,
    "priceOpen": 118.9,
    "priceAverage": 117.49791653473498,
    "priceClose": 120.9,
    "priceBasic": 122,
    "totalVolume": 3158200,
    "dealVolume": 3158200,
    "putthroughVolume": 0,
    "totalValue": 371081920000,
    "putthroughValue": 0,
    "buyForeignQuantity": 490500,
    "buyForeignValue": 57632728060.287506,
    "sellForeignQuantity": 440050,
    "sellForeignValue": 51704958171.11012,
    "buyCount": 3341,
    "buyQuantity": 3987232,
    "sellCount": 2721,
    "sellQuantity": 4216410,
    "adjRatio": 1,
    "currentForeignRoom": 828106,
    "propTradingNetDealValue": -878970000,
    "propTradingNetPTValue": 0,
    "propTradingNetValue": -878970000,
    "unit": 1000,
    "priceChange": -1.0999999999999943,
    "returnPct": -0.9016393442622904
  },
  {
    "date": "2026-03-05T00:00:00",
    "symbol": "PNJ",
    "priceHigh": 119.8,
    "priceLow": 113,
    "priceOpen": 119.8,
    "priceAverage": 116.07218531391614,
    "priceClose": 116,
    "priceBasic": 120.9,
    "totalVolume": 2407200,
    "dealVolume": 2272900,
    "putthroughVolume": 134300,
    "totalValue": 279408939600,
    "putthroughValue": 15588469600,
    "buyForeignQuantity": 572427,
    "buyForeignValue": 66442852822.68907,
    "sellForeignQuantity": 1022700,
    "sellForeignValue": 118707023920.54204,
    "buyCount": 3110,
    "buyQuantity": 3429240,
    "sellCount": 2070,
    "sellQuantity": 3919727,
    "adjRatio": 1,
    "currentForeignRoom": 830129,
    "propTradingNetDealValue": -8917720000,
    "propTradingNetPTValue": 0,
    "propTradingNetValue": -8917720000,
    "unit": 1000,
    "priceChange": -4.900000000000006,
    "returnPct": -4.052936311000831
  },
  {
    "date": "2026-03-06T00:00:00",
    "symbol": "PNJ",
    "priceHigh": 116,
    "priceLow": 110.6,
    "priceOpen": 115,
    "priceAverage": 113.16542303617376,
    "priceClose": 114.5,
    "priceBasic": 116,
    "totalVolume": 2642800,
    "dealVolume": 2642800,
    "putthroughVolume": 0,
    "totalValue": 299073580000,
    "putthroughValue": 0,
    "buyForeignQuantity": 708413,
    "buyForeignValue": 80167856829.32495,
    "sellForeignQuantity": 312400,
    "sellForeignValue": 35352878156.50068,
    "buyCount": 3533,
    "buyQuantity": 4544994,
    "sellCount": 2333,
    "sellQuantity": 3808502,
    "adjRatio": 1,
    "currentForeignRoom": 558456,
    "propTradingNetDealValue": 3190540000,
    "propTradingNetPTValue": 0,
    "propTradingNetValue": 3190540000,
    "unit": 1000,
    "priceChange": -1.5,
    "returnPct": -1.293103448275862
  },
  {
    "date": "2026-03-09T00:00:00",
    "symbol": "PNJ",
    "priceHigh": 108.9,
    "priceLow": 106.5,
    "priceOpen": 106.7,
    "priceAverage": 106.5721911364199,
    "priceClose": 106.5,
    "priceBasic": 114.5,
    "totalVolume": 2140100,
    "dealVolume": 2019500,
    "putthroughVolume": 120600,
    "totalValue": 228066440000,
    "putthroughValue": 12843900000,
    "buyForeignQuantity": 449101,
    "buyForeignValue": 47861677611.55732,
    "sellForeignQuantity": 202237,
    "sellForeignValue": 21552840218.85615,
    "buyCount": 1339,
    "buyQuantity": 2296184,
    "sellCount": 1591,
    "sellQuantity": 4208875,
    "adjRatio": 1,
    "currentForeignRoom": 543742,
    "propTradingNetDealValue": 2717430000,
    "propTradingNetPTValue": 0,
    "propTradingNetValue": 2717430000,
    "unit": 1000,
    "priceChange": -8,
    "returnPct": -6.986899563318777
  },
  {
    "date": "2026-03-10T00:00:00",
    "symbol": "PNJ",
    "priceHigh": 113.7,
    "priceLow": 108.7,
    "priceOpen": 113.7,
    "priceAverage": 111.59413163716815,
    "priceClose": 113.5,
    "priceBasic": 106.5,
    "totalVolume": 1808000,
    "dealVolume": 1808000,
    "putthroughVolume": 0,
    "totalValue": 201762190000,
    "putthroughValue": 0,
    "buyForeignQuantity": 475100,
    "buyForeignValue": 53018371940.81858,
    "sellForeignQuantity": 12900,
    "sellForeignValue": 1439564298.119469,
    "buyCount": 1779,
    "buyQuantity": 4049500,
    "sellCount": 1540,
    "sellQuantity": 2349308,
    "adjRatio": 1,
    "currentForeignRoom": 52,
    "propTradingNetDealValue": -231360000,
    "propTradingNetPTValue": 0,
    "propTradingNetValue": -231360000,
    "unit": 1000,
    "priceChange": 7,
    "returnPct": 6.572769953051644
  },
  {
    "date": "2026-03-11T00:00:00",
    "symbol": "PNJ",
    "priceHigh": 119.5,
    "priceLow": 111.5,
    "priceOpen": 113.3,
    "priceAverage": 116.86378515564303,
    "priceClose": 119,
    "priceBasic": 113.5,
    "totalVolume": 2117700,
    "dealVolume": 1930700,
    "putthroughVolume": 187000,
    "totalValue": 247763762000,
    "putthroughValue": 22134852000,
    "buyForeignQuantity": 580401,
    "buyForeignValue": 67827857768.12037,
    "sellForeignQuantity": 300200,
    "sellForeignValue": 35082508303.72404,
    "buyCount": 2128,
    "buyQuantity": 3396352,
    "sellCount": 2270,
    "sellQuantity": 3103696,
    "adjRatio": 1,
    "currentForeignRoom": 51,
    "propTradingNetDealValue": 862800000,
    "propTradingNetPTValue": 0,
    "propTradingNetValue": 862800000,
    "unit": 1000,
    "priceChange": 5.5,
    "returnPct": 4.845814977973569
  },
  {
    "date": "2026-03-12T00:00:00",
    "symbol": "PNJ",
    "priceHigh": 118.6,
    "priceLow": 115,
    "priceOpen": 118.6,
    "priceAverage": 116.78330157456624,
    "priceClose": 117.9,
    "priceBasic": 119,
    "totalVolume": 1546000,
    "dealVolume": 997100,
    "putthroughVolume": 548900,
    "totalValue": 180546818700,
    "putthroughValue": 64102188700,
    "buyForeignQuantity": 792151,
    "buyForeignValue": 92510009125.59422,
    "sellForeignQuantity": 715000,
    "sellForeignValue": 83500060625.81487,
    "buyCount": 1208,
    "buyQuantity": 2244211,
    "sellCount": 2161,
    "sellQuantity": 2908629,
    "adjRatio": 1,
    "currentForeignRoom": 5000,
    "propTradingNetDealValue": 3837850000,
    "propTradingNetPTValue": 0,
    "propTradingNetValue": 3837850000,
    "unit": 1000,
    "priceChange": -1.0999999999999943,
    "returnPct": -0.9243697478991548
  },
  {
    "date": "2026-03-13T00:00:00",
    "symbol": "PNJ",
    "priceHigh": 117.4,
    "priceLow": 114.9,
    "priceOpen": 115,
    "priceAverage": 116.56914863190008,
    "priceClose": 116.9,
    "priceBasic": 117.9,
    "totalVolume": 1048900,
    "dealVolume": 1048900,
    "putthroughVolume": 0,
    "totalValue": 122269380000,
    "putthroughValue": 0,
    "buyForeignQuantity": 186100,
    "buyForeignValue": 21693518560.396606,
    "sellForeignQuantity": 373200,
    "sellForeignValue": 43503606269.42511,
    "buyCount": 1252,
    "buyQuantity": 1789707,
    "sellCount": 1700,
    "sellQuantity": 2017198,
    "adjRatio": 1,
    "currentForeignRoom": 0,
    "propTradingNetDealValue": 576500000,
    "propTradingNetPTValue": 0,
    "propTradingNetValue": 576500000,
    "unit": 1000,
    "priceChange": -1,
    "returnPct": -0.8481764206955046
  },
  {
    "date": "2026-03-16T00:00:00",
    "symbol": "PNJ",
    "priceHigh": 118.1,
    "priceLow": 114.2,
    "priceOpen": 115.1,
    "priceAverage": 116.60723344947735,
    "priceClose": 118,
    "priceBasic": 116.9,
    "totalVolume": 932500,
    "dealVolume": 717500,
    "putthroughVolume": 215000,
    "totalValue": 108736195000,
    "putthroughValue": 25070505000,
    "buyForeignQuantity": 410100,
    "buyForeignValue": 47820626437.63066,
    "sellForeignQuantity": 242500,
    "sellForeignValue": 28277254111.498257,
    "buyCount": 954,
    "buyQuantity": 1678868,
    "sellCount": 1270,
    "sellQuantity": 1412230,
    "adjRatio": 1,
    "currentForeignRoom": 0,
    "propTradingNetDealValue": -464800000,
    "propTradingNetPTValue": 0,
    "propTradingNetValue": -464800000,
    "unit": 1000,
    "priceChange": 1.0999999999999943,
    "returnPct": 0.9409751924721935
  },
  {
    "date": "2026-03-17T00:00:00",
    "symbol": "PNJ",
    "priceHigh": 119.2,
    "priceLow": 115.4,
    "priceOpen": 118.7,
    "priceAverage": 117.54774903530085,
    "priceClose": 117.7,
    "priceBasic": 118,
    "totalVolume": 913800,
    "dealVolume": 699700,
    "putthroughVolume": 214100,
    "totalValue": 107415186800,
    "putthroughValue": 25167026800,
    "buyForeignQuantity": 302600,
    "buyForeignValue": 35569948858.08204,
    "sellForeignQuantity": 541500,
    "sellForeignValue": 63652106102.61541,
    "buyCount": 1463,
    "buyQuantity": 1297058,
    "sellCount": 1616,
    "sellQuantity": 2275556,
    "adjRatio": 1,
    "currentForeignRoom": 0,
    "propTradingNetDealValue": 4156030000,
    "propTradingNetPTValue": 0,
    "propTradingNetValue": 4156030000,
    "unit": 1000,
    "priceChange": -0.29999999999999716,
    "returnPct": -0.2542372881355908
  },
  {
    "date": "2026-03-18T00:00:00",
    "symbol": "PNJ",
    "priceHigh": 117.7,
    "priceLow": 113.5,
    "priceOpen": 117.7,
    "priceAverage": 115.10394946505805,
    "priceClose": 115,
    "priceBasic": 117.7,
    "totalVolume": 978600,
    "dealVolume": 878600,
    "putthroughVolume": 100000,
    "totalValue": 112618130000,
    "putthroughValue": 11487800000,
    "buyForeignQuantity": 304200,
    "buyForeignValue": 35014621427.27066,
    "sellForeignQuantity": 595367,
    "sellForeignValue": 68529093081.163216,
    "buyCount": 1869,
    "buyQuantity": 1602337,
    "sellCount": 1520,
    "sellQuantity": 2101502,
    "adjRatio": 1,
    "currentForeignRoom": 71400,
    "propTradingNetDealValue": 676100000,
    "propTradingNetPTValue": 0,
    "propTradingNetValue": 676100000,
    "unit": 1000,
    "priceChange": -2.700000000000003,
    "returnPct": -2.2939677145284643
  },
  {
    "date": "2026-03-19T00:00:00",
    "symbol": "PNJ",
    "priceHigh": 115.5,
    "priceLow": 112.1,
    "priceOpen": 113,
    "priceAverage": 114.32644755029949,
    "priceClose": 114.9,
    "priceBasic": 115,
    "totalVolume": 895700,
    "dealVolume": 651100,
    "putthroughVolume": 244600,
    "totalValue": 102504483400,
    "putthroughValue": 28066533400,
    "buyForeignQuantity": 343200,
    "buyForeignValue": 39236836799.26279,
    "sellForeignQuantity": 316600,
    "sellForeignValue": 36195753294.42482,
    "buyCount": 1260,
    "buyQuantity": 1995414,
    "sellCount": 930,
    "sellQuantity": 1234274,
    "adjRatio": 1,
    "currentForeignRoom": 0,
    "propTradingNetDealValue": -7741020000,
    "propTradingNetPTValue": 0,
    "propTradingNetValue": -7741020000,
    "unit": 1000,
    "priceChange": -0.09999999999999432,
    "returnPct": -0.08695652173912549
  },
  {
    "date": "2026-03-20T00:00:00",
    "symbol": "PNJ",
    "priceHigh": 114.9,
    "priceLow": 112.6,
    "priceOpen": 114.9,
    "priceAverage": 113.07408634636,
    "priceClose": 114.2,
    "priceBasic": 114.9,
    "totalVolume": 1626100,
    "dealVolume": 1026100,
    "putthroughVolume": 600000,
    "totalValue": 183869720000,
    "putthroughValue": 67844400000,
    "buyForeignQuantity": 1058000,
    "buyForeignValue": 119632383354.44888,
    "sellForeignQuantity": 600000,
    "sellForeignValue": 67844451807.816,
    "buyCount": 1459,
    "buyQuantity": 3244942,
    "sellCount": 1716,
    "sellQuantity": 1942520,
    "adjRatio": 1,
    "currentForeignRoom": 0,
    "propTradingNetDealValue": -9995730000,
    "propTradingNetPTValue": 0,
    "propTradingNetValue": -9995730000,
    "unit": 1000,
    "priceChange": -0.7000000000000028,
    "returnPct": -0.6092254134029615
  },
  {
    "date": "2026-03-23T00:00:00",
    "symbol": "PNJ",
    "priceHigh": 112,
    "priceLow": 106.3,
    "priceOpen": 111.1,
    "priceAverage": 107.78249104436485,
    "priceClose": 106.3,
    "priceBasic": 114.2,
    "totalVolume": 2469400,
    "dealVolume": 1814500,
    "putthroughVolume": 654900,
    "totalValue": 266157761800,
    "putthroughValue": 70586431800,
    "buyForeignQuantity": 975967,
    "buyForeignValue": 105192154437.09563,
    "sellForeignQuantity": 984700,
    "sellForeignValue": 106133418931.38606,
    "buyCount": 1658,
    "buyQuantity": 2619062,
    "sellCount": 2212,
    "sellQuantity": 4086590,
    "adjRatio": 1,
    "currentForeignRoom": 0,
    "propTradingNetDealValue": 2438940000,
    "propTradingNetPTValue": 0,
    "propTradingNetValue": 2438940000,
    "unit": 1000,
    "priceChange": -7.900000000000006,
    "returnPct": -6.917688266199655
  },
  {
    "date": "2026-03-24T00:00:00",
    "symbol": "PNJ",
    "priceHigh": 108.5,
    "priceLow": 106.2,
    "priceOpen": 107.2,
    "priceAverage": 107.02281164195497,
    "priceClose": 108.5,
    "priceBasic": 106.3,
    "totalVolume": 1540700,
    "dealVolume": 910500,
    "putthroughVolume": 630200,
    "totalValue": 164890164600,
    "putthroughValue": 67445894600,
    "buyForeignQuantity": 630267,
    "buyForeignValue": 67452946425.14003,
    "sellForeignQuantity": 903600,
    "sellForeignValue": 96705812599.67052,
    "buyCount": 1278,
    "buyQuantity": 2372366,
    "sellCount": 1971,
    "sellQuantity": 1964961,
    "adjRatio": 1,
    "currentForeignRoom": 0,
    "propTradingNetDealValue": -95610000,
    "propTradingNetPTValue": 0,
    "propTradingNetValue": -95610000,
    "unit": 1000,
    "priceChange": 2.200000000000003,
    "returnPct": 2.069614299153342
  },
  {
    "date": "2026-03-25T00:00:00",
    "symbol": "PNJ",
    "priceHigh": 111,
    "priceLow": 108.3,
    "priceOpen": 109.5,
    "priceAverage": 109.52620267812861,
    "priceClose": 111,
    "priceBasic": 108.5,
    "totalVolume": 1812000,
    "dealVolume": 1209800,
    "putthroughVolume": 602200,
    "totalValue": 198444218900,
    "putthroughValue": 65939418900,
    "buyForeignQuantity": 618100,
    "buyForeignValue": 67698145875.351295,
    "sellForeignQuantity": 834633,
    "sellForeignValue": 91414183119.85452,
    "buyCount": 1202,
    "buyQuantity": 2537636,
    "sellCount": 1339,
    "sellQuantity": 2313184,
    "adjRatio": 1,
    "currentForeignRoom": 305167,
    "propTradingNetDealValue": -1809410000,
    "propTradingNetPTValue": 0,
    "propTradingNetValue": -1809410000,
    "unit": 1000,
    "priceChange": 2.5,
    "returnPct": 2.3041474654377883
  },
  {
    "date": "2026-03-26T00:00:00",
    "symbol": "PNJ",
    "priceHigh": 111.5,
    "priceLow": 103.3,
    "priceOpen": 111,
    "priceAverage": 105.20058420892009,
    "priceClose": 106,
    "priceBasic": 111,
    "totalVolume": 3016800,
    "dealVolume": 2293700,
    "putthroughVolume": 723100,
    "totalValue": 317038296800,
    "putthroughValue": 75739716800,
    "buyForeignQuantity": 1007400,
    "buyForeignValue": 105979068532.0661,
    "sellForeignQuantity": 843000,
    "sellForeignValue": 88684092488.11963,
    "buyCount": 3963,
    "buyQuantity": 3931811,
    "sellCount": 2148,
    "sellQuantity": 3854729,
    "adjRatio": 1,
    "currentForeignRoom": 0,
    "propTradingNetDealValue": -76173230000,
    "propTradingNetPTValue": 0,
    "propTradingNetValue": -76173230000,
    "unit": 1000,
    "priceChange": -5,
    "returnPct": -4.504504504504505
  },
  {
    "date": "2026-03-27T00:00:00",
    "symbol": "PNJ",
    "priceHigh": 109.9,
    "priceLow": 100.7,
    "priceOpen": 102.8,
    "priceAverage": 104.72322010676997,
    "priceClose": 109.9,
    "priceBasic": 106,
    "totalVolume": 2346700,
    "dealVolume": 2116700,
    "putthroughVolume": 230000,
    "totalValue": 245834020000,
    "putthroughValue": 24166380000,
    "buyForeignQuantity": 568702,
    "buyForeignValue": 59556304721.16029,
    "sellForeignQuantity": 691800,
    "sellForeignValue": 72447523669.86346,
    "buyCount": 3724,
    "buyQuantity": 4727252,
    "sellCount": 3485,
    "sellQuantity": 2794648,
    "adjRatio": 1,
    "currentForeignRoom": 30,
    "propTradingNetDealValue": -47792520000,
    "propTradingNetPTValue": 0,
    "propTradingNetValue": -47792520000,
    "unit": 1000,
    "priceChange": 3.9000000000000057,
    "returnPct": 3.6792452830188735
  },
  {
    "date": "2026-03-30T00:00:00",
    "symbol": "PNJ",
    "priceHigh": 108,
    "priceLow": 105.1,
    "priceOpen": 105.2,
    "priceAverage": 107.16769550748751,
    "priceClose": 108,
    "priceBasic": 109.9,
    "totalVolume": 1397400,
    "dealVolume": 1202000,
    "putthroughVolume": 195400,
    "totalValue": 149756197200,
    "putthroughValue": 20940627200,
    "buyForeignQuantity": 560466,
    "buyForeignValue": 60063849630.2995,
    "sellForeignQuantity": 742900,
    "sellForeignValue": 79614880992.51248,
    "buyCount": 1574,
    "buyQuantity": 3443354,
    "sellCount": 2598,
    "sellQuantity": 2668572,
    "adjRatio": 1,
    "currentForeignRoom": 35000,
    "propTradingNetDealValue": 7182380000,
    "propTradingNetPTValue": 0,
    "propTradingNetValue": 7182380000,
    "unit": 1000,
    "priceChange": -1.9000000000000057,
    "returnPct": -1.7288444040036446
  },
  {
    "date": "2026-03-31T00:00:00",
    "symbol": "PNJ",
    "priceHigh": 110,
    "priceLow": 107.1,
    "priceOpen": 108,
    "priceAverage": 108.49446454898806,
    "priceClose": 108,
    "priceBasic": 108,
    "totalVolume": 1582200,
    "dealVolume": 1492200,
    "putthroughVolume": 90000,
    "totalValue": 171659900000,
    "putthroughValue": 9764460000,
    "buyForeignQuantity": 375020,
    "buyForeignValue": 40687594095.16151,
    "sellForeignQuantity": 600278,
    "sellForeignValue": 65126840190.53746,
    "buyCount": 1232,
    "buyQuantity": 2697705,
    "sellCount": 1986,
    "sellQuantity": 2664121,
    "adjRatio": 1,
    "currentForeignRoom": 46,
    "propTradingNetDealValue": 2149980000,
    "propTradingNetPTValue": 0,
    "propTradingNetValue": 2149980000,
    "unit": 1000,
    "priceChange": 0,
    "returnPct": 0
  },
  {
    "date": "2026-04-01T00:00:00",
    "symbol": "PNJ",
    "priceHigh": 109.7,
    "priceLow": 107.9,
    "priceOpen": 109.1,
    "priceAverage": 108.82055350553505,
    "priceClose": 109.3,
    "priceBasic": 108,
    "totalVolume": 813000,
    "dealVolume": 813000,
    "putthroughVolume": 0,
    "totalValue": 88471110000,
    "putthroughValue": 0,
    "buyForeignQuantity": 28360,
    "buyForeignValue": 3086150897.416974,
    "sellForeignQuantity": 16800,
    "sellForeignValue": 1828185298.892989,
    "buyCount": 0,
    "buyQuantity": 0,
    "sellCount": 0,
    "sellQuantity": 0,
    "adjRatio": 1,
    "currentForeignRoom": 4,
    "propTradingNetDealValue": null,
    "propTradingNetPTValue": null,
    "propTradingNetValue": null,
    "unit": 1000,
    "priceChange": 1.2999999999999972,
    "returnPct": 1.203703703703701
  }
]
